ai4ce_helpers/__init__.py
ai4ce_helpers/_backend_calls.py
ai4ce_helpers/data/backend_sys_default.json
ai4ce_helpers/functions.py
ai4ce_helpers/functions_components.py
ai4ce_helpers/functions_projects.py
ai4ce_helpers/logging_setup.py
ai4ce_helpers/renamed_functions.py
ai4ce_helpers/streamlit_functions.py
ai4ce_helpers-0.17.8.dist-info/licenses/COPYING
ai4ce_helpers-0.17.8.dist-info/licenses/COPYING.LESSER
ai4ce_helpers-0.17.8.dist-info/licenses/LICENSE
ai4ce_helpers-0.17.8.dist-info/METADATA
ai4ce_helpers-0.17.8.dist-info/WHEEL
ai4ce_helpers-0.17.8.dist-info/RECORD
