Metadata-Version: 2.4
Name: ai4ce-helpers
Version: 0.17.8
Summary: Functions to help interact with the AI4CE backend
License: LICENSE
License-File: COPYING
License-File: COPYING.LESSER
License-File: LICENSE
Author: Alexander Salge
Author-email: wildfire_small467@simplelogin.com
Requires-Python: >=3.11, <4
Classifier: Operating System :: OS Independent
Classifier: Development Status :: 3 - Alpha
Classifier: Environment :: Web Environment
Classifier: Intended Audience :: Developers
Classifier: Programming Language :: Python :: 3 :: Only
Classifier: Programming Language :: Python :: 3.11
Classifier: Programming Language :: Python :: 3.12
Classifier: Programming Language :: Python :: 3.13
Requires-Dist: deprecated (>=1,<2)
Requires-Dist: httpx (>=0,<1)
Requires-Dist: streamlit (>=1,<2)
Requires-Dist: streamlit-mermaid (>=0.3.0,<0.4.0)
Project-URL: Homepage, https://gitlab.com/ai4ce/public-info
Project-URL: Repository, https://gitlab.com/ai4ce/ai4ce-helpers
